{
  "elias": {
    "nicknames": [
      "Elias"
    ],
    "sets": [
      {
        "abilities": [
          "justified",
          "insomnia"
        ],
        "items": [
          "choiceband"
        ],
        "moves": [
          "swordsedge",
          "bindingsword",
          "sacredsword"
        ],
        "lockedMoves": [
          "soulsword"
        ],
        "level": 84
      }
    ]
  },
  "mothmowl": {
    "nicknames": [
      "Mothmowl"
    ],
    "sets": [
      {
        "abilities": [
          "intimidate"
        ],
        "items": [
          "heavydutyboots"
        ],
        "moves": [
          "cryptid",
          "paranoia",
          "bravebird"
        ],
        "lockedMoves": [
          "purefear"
        ],
        "level": 84
      }
    ]
  },
  "coommate": {
    "nicknames": [
      "Coommate"
    ],
    "sets": [
      {
        "abilities": [
          "berserker"
        ],
        "items": [
          "choicescarf"
        ],
        "moves": [
          "warpaway",
          "odynocharge",
          "burningpassion"
        ],
        "lockedMoves": [
          "invasion"
        ],
        "level": 84
      }
    ]
  },
  "drgnchamber": {
    "nicknames": [
      "Chambermaid"
    ],
    "sets": [
      {
        "abilities": [
          "serenegrace"
        ],
        "items": [
          "angelpowder"
        ],
        "moves": [
          "steamclean",
          "sewing",
          "yatanokagami"
        ],
        "lockedMoves": [
          "dusttornado"
        ],
        "level": 84
      }
    ]
  },
  "alterlanta": {
    "nicknames": [
      "Alterlanta"
    ],
    "sets": [
      {
        "abilities": [
          "berserker"
        ],
        "items": [
          "lifeorb"
        ],
        "moves": [
          "cbt",
          "tauroskiathermokrasia",
          "extremespeed"
        ],
        "lockedMoves": [
          "agility"
        ],
        "level": 84
      }
    ]
  },
  "dragurve": {
    "nicknames": [
      "Dragurve"
    ],
    "sets": [
      {
        "abilities": [
          "adaptability"
        ],
        "items": [
          "lifeorb"
        ],
        "moves": [
          "spacialrend",
          "voltswitch",
          "thunderwave",
          "trickroom"
        ],
        "lockedMoves": [
          "dracometeor"
        ],
        "level": 84
      }
    ]
  },
  "standopurplehaze": {
    "nicknames": [
      "Stando-PurpleHaze"
    ],
    "sets": [
      {
        "abilities": [
          "poisonheal"
        ],
        "items": [
          "toxicorb"
        ],
        "moves": [
          "drainpunch",
          "protect",
          "poisonjab",
          "earthquake"
        ],
        "lockedMoves": [
          "purplehaze",
          "pleaguefrezy"
        ],
        "level": 84
      }
    ]
  },
  "standohorus": {
    "nicknames": [
      "Stando-Horus"
    ],
    "sets": [
      {
        "abilities": [
          "compoundeyes"
        ],
        "items": [
          "heavydutyboots"
        ],
        "moves": [
          "focusblast",
          "stoneedge",
          "taunt",
          "earthquake"
        ],
        "lockedMoves": [
          "iciclecrash",
          "bravebird"
        ],
        "level": 84
      }
    ]
  },
  "dmcdante": {
    "nicknames": [
      "Dmcdante"
    ],
    "sets": [
      {
        "abilities": [
          "regenerator"
        ],
        "items": [
          "heavydutyboots"
        ],
        "moves": [
          "knockoff",
          "toxic",
          "taunt",
          "thunderwave",
          "earthquake"
        ],
        "lockedMoves": [
          "pizzaspin",
          "swordsedge"
        ],
        "level": 84
      }
    ]
  },
  "btyranitar": {
    "nicknames": [
      "beta AF"
    ],
    "sets": [
      {
        "abilities": [
          "sandstream"
        ],
        "items": [
          "chopleberry"
        ],
        "moves": [
          "flintstrike",
          "fireblast",
          "stealthrock",
          "thunderbolt",
          "hydropump",
          "icebeam",
          "thunderwave"
        ],
        "lockedMoves": [
          "earthquake"
        ],
        "level": 84
      }
    ]
  },
  "wackchad": {
    "nicknames": [
      "cahd"
    ],
    "sets": [
      {
        "abilities": [
          "intimidate"
        ],
        "items": [
          "lifeorb",
          "heavydutyboots",
          "choicescarf"
        ],
        "moves": [
          "playrough",
          "pursuit",
          "bloodhound",
          "firefang",
          "crunch"
        ],
        "lockedMoves": [
          "cbt",
          "closecombat"
        ],
        "level": 84
      }
    ]
  },
  "warshin": {
    "nicknames": [
      "Warshin"
    ],
    "sets": [
      {
        "abilities": [
          "swiftswim",
          "drizzle"
        ],
        "items": [
          "lifeorb",
          "heavydutyboots",
          "choicescarf"
        ],
        "moves": [
          "knockoff",
          "icebeam",
          "crosschop"
        ],
        "lockedMoves": [
          "sharkbite"
        ],
        "level": 84
      }
    ]
  },
  "mylph": {
    "nicknames": [
      "Mylph"
    ],
    "sets": [
      {
        "abilities": [
          "levitate"
        ],
        "items": [
          "lifeorb",
          "heavydutyboots",
          "angelpowder"
        ],
        "moves": [
          "milkdrink",
          "thunderwave",
          "moonblast",
          "healbell",
          "foulplay"
        ],
        "lockedMoves": [
          "venusburst"
        ],
        "level": 84
      }
    ]
  },
  "knood": {
    "nicknames": [
      "Knood"
    ],
    "sets": [
      {
        "abilities": [
          "battlearmor"
        ],
        "items": [
          "lifeorb",
          "heavydutyboots",
          "angelpowder"
        ],
        "moves": [
          "armorburst",
          "bodypress",
          "ironroot",
          "synthesis",
          "toxic"
        ],
        "lockedMoves": [
          "armorcrash",
          "barkpress"
        ],
        "level": 84
      }
    ]
  },
  "swanaper": {
    "nicknames": [
      "Swanaper"
    ],
    "sets": [
      {
        "abilities": [
          "serenegrace",
          "roughskin"
        ],
        "items": [
          "rockyhelmet",
          "heavydutyboots",
          "angelpowder"
        ],
        "moves": [
          "swordsdance",
          "painsplit",
          "leafblade",
          "drillrun",
          "tailwind"
        ],
        "lockedMoves": [
          "aerialrace"
        ],
        "level": 84
      }
    ]
  },
  "doita": {
    "nicknames": [
      "Doita"
    ],
    "sets": [
      {
        "abilities": [
          "victorystar",
          "pride"
        ],
        "items": [
          "assaultvest",
          "heavydutyboots",
          "lifeorb"
        ],
        "moves": [
          "abruption",
          "boomburst",
          "flamecharge",
          "scald",
          "heatwave"
        ],
        "lockedMoves": [
          "bassdrop"
        ],
        "level": 84
      }
    ]
  },
  "neonazi": {
    "nicknames": [
      "Neonazi"
    ],
    "sets": [
      {
        "abilities": [
          "protean"
        ],
        "items": [
          "lifeorb",
          "assaultvest"
        ],
        "moves": [
          "flamethrower",
          "flashcannon",
          "focusblast",
          "energyball",
          "voltswitch",
          "thunderbolt",
          "powergem",
          "signalbeam",
          "psychic",
          "flashball"
        ],
        
        "level": 84
      }
    ]
  },
  "carmillapire": {
    "nicknames": [
      "Carmillapire"
    ],
    "sets": [
      {
        "abilities": [
          "siphon"
        ],
        "items": [
          "angelpowder"
        ],
        "moves": [
          "bloodsiphon",
          "gigadrain",
          "vampirebite"
        ],
        "lockedMoves": [
          "bloodbite"
        ],
        "level": 84
      }
    ]
  }
}